{
    "name": "Integration Apify",
    "flow": [
        {
            "id": 1,
            "module": "apify:runActorNew",
            "version": 1,
            "parameters": {
                "__IMTCONN__": 4023612
            },
            "mapper": {
                "actor_search_type": "user",
                "runSync": true,
                "actorId": "nwua9Gu5YrADL7ZDj",
                "inputBodynwua9Gu5YrADL7ZDj": "{\r\n    \"includeWebResults\": true,\r\n    \"language\": \"en\",\r\n    \"locationQuery\": \"Nairobi,Kenya\",\r\n    \"maxCrawledPlacesPerSearch\": 5,\r\n    \"maxImages\": 0,\r\n    \"maximumLeadsEnrichmentRecords\": 0,\r\n    \"scrapeContacts\": false,\r\n    \"scrapeDirectories\": false,\r\n    \"scrapeImageAuthors\": false,\r\n    \"scrapePlaceDetailPage\": false,\r\n    \"scrapeReviewsPersonalData\": true,\r\n    \"scrapeSocialMediaProfiles\": {\r\n        \"facebooks\": false,\r\n        \"instagrams\": false,\r\n        \"tiktoks\": false,\r\n        \"twitters\": false,\r\n        \"youtubes\": false\r\n    },\r\n    \"scrapeTableReservationProvider\": false,\r\n    \"searchStringsArray\": [\r\n        \"restaurant\"\r\n    ],\r\n    \"skipClosedPlaces\": false\r\n}"
            },
            "metadata": {
                "designer": {
                    "x": 0,
                    "y": 0
                },
                "restore": {
                    "parameters": {
                        "__IMTCONN__": {
                            "label": "My Apify API Token connection (ratimmohammed96@gmail.com)",
                            "data": {
                                "scoped": "true",
                                "connection": "apify"
                            }
                        }
                    },
                    "expect": {
                        "actor_search_type": {
                            "label": "Recently used Actors"
                        },
                        "runSync": {
                            "mode": "chose"
                        },
                        "memory": {
                            "mode": "chose",
                            "label": "Empty"
                        },
                        "actorId": {
                            "mode": "chose",
                            "label": "Google Maps Scraper (compass/crawler-google-places)"
                        }
                    }
                },
                "parameters": [
                    {
                        "name": "__IMTCONN__",
                        "type": "account:apify2,apify",
                        "label": "Connection",
                        "required": true
                    }
                ],
                "expect": [
                    {
                        "name": "actor_search_type",
                        "type": "select",
                        "label": "Search Actors from",
                        "required": true,
                        "validate": {
                            "enum": [
                                "user",
                                "store"
                            ]
                        }
                    },
                    {
                        "name": "runSync",
                        "type": "boolean",
                        "label": "Run synchronously",
                        "required": true
                    },
                    {
                        "name": "build",
                        "type": "text",
                        "label": "Build"
                    },
                    {
                        "name": "timeout",
                        "type": "uinteger",
                        "label": "Timeout"
                    },
                    {
                        "name": "memory",
                        "type": "select",
                        "label": "Memory",
                        "validate": {
                            "enum": [
                                128,
                                256,
                                512,
                                1024,
                                2048,
                                4096,
                                8192,
                                16384,
                                32768
                            ]
                        }
                    },
                    {
                        "name": "actorId",
                        "type": "select",
                        "label": "Actor",
                        "required": true
                    },
                    {
                        "name": "inputBodynwua9Gu5YrADL7ZDj",
                        "type": "text",
                        "label": "Input JSON",
                        "required": true
                    },
                    {
                        "name": "maxTotalChargeUsd",
                        "type": "number",
                        "label": "Maximum cost per run"
                    },
                    {
                        "name": "maxItems",
                        "type": "hidden",
                        "label": "Maximum charged results"
                    }
                ]
            }
        },
        {
            "id": 3,
            "module": "apify:fetchDatasetItems",
            "version": 1,
            "parameters": {
                "__IMTCONN__": 4002834
            },
            "mapper": {
                "type": "clean",
                "limit": "100",
                "format": "json",
                "datasetId": "{{1.defaultDatasetId}}"
            },
            "metadata": {
                "designer": {
                    "x": 300,
                    "y": 0
                },
                "restore": {
                    "expect": {
                        "type": {
                            "mode": "chose",
                            "label": "Clean"
                        },
                        "format": {
                            "mode": "chose",
                            "label": "JSON"
                        }
                    },
                    "parameters": {
                        "__IMTCONN__": {
                            "data": {
                                "scoped": "true",
                                "connection": "apify"
                            },
                            "label": "My Apify API Token connection (borumohammed5@gmail.com)"
                        }
                    }
                },
                "parameters": [
                    {
                        "name": "__IMTCONN__",
                        "type": "account:apify2,apify",
                        "label": "Connection",
                        "required": true
                    }
                ],
                "expect": [
                    {
                        "name": "datasetId",
                        "type": "text",
                        "label": "Dataset ID",
                        "required": true
                    },
                    {
                        "name": "type",
                        "type": "select",
                        "label": "Data transformation",
                        "required": true,
                        "validate": {
                            "enum": [
                                "clean",
                                "simplified",
                                "none"
                            ]
                        }
                    },
                    {
                        "name": "format",
                        "type": "select",
                        "label": "Format",
                        "required": true,
                        "validate": {
                            "enum": [
                                "json",
                                "csv",
                                "html",
                                "xml",
                                "rss",
                                "xlsx"
                            ]
                        }
                    },
                    {
                        "name": "limit",
                        "type": "uinteger",
                        "label": "Limit",
                        "validate": {
                            "max": 100000,
                            "min": 1
                        }
                    },
                    {
                        "name": "offset",
                        "type": "uinteger",
                        "label": "Offset",
                        "validate": {
                            "min": 0
                        }
                    }
                ]
            }
        },
        {
            "id": 5,
            "module": "apify:runActorNew",
            "version": 1,
            "parameters": {
                "__IMTCONN__": 4023612
            },
            "mapper": {
                "actor_search_type": "user",
                "runSync": true,
                "actorId": "9Sk4JJhEma9vBKqrg",
                "inputBody9Sk4JJhEma9vBKqrg": "{\r\n    \"considerChildFrames\": true,\r\n    \"maxDepth\": 5,\r\n    \"maxRequests\": 6,\r\n    \"maxRequestsPerStartUrl\": 3,\r\n    \"maximumLeadsEnrichmentRecords\": 0,\r\n    \"mergeContacts\": true,\r\n    \"sameDomain\": false,\r\n    \"scrapeSocialMediaProfiles\": {\r\n        \"facebooks\": true,\r\n        \"instagrams\": true,\r\n        \"tiktoks\": true,\r\n        \"twitters\": true,\r\n        \"youtubes\": true\r\n    },\r\n    \"startUrls\": [\r\n        {\r\n            \"url\": \"{{3.webResults[].url}}\"\r\n        }\r\n    ],\r\n    \"useBrowser\": false\r\n}"
            },
            "metadata": {
                "designer": {
                    "x": 600,
                    "y": 0
                },
                "restore": {
                    "parameters": {
                        "__IMTCONN__": {
                            "label": "My Apify API Token connection (ratimmohammed96@gmail.com)",
                            "data": {
                                "scoped": "true",
                                "connection": "apify"
                            }
                        }
                    },
                    "expect": {
                        "actor_search_type": {
                            "label": "Recently used Actors"
                        },
                        "runSync": {
                            "mode": "chose"
                        },
                        "memory": {
                            "mode": "chose",
                            "label": "Empty"
                        },
                        "actorId": {
                            "mode": "chose",
                            "label": "Contact Details Scraper (vdrmota/contact-info-scraper)"
                        }
                    }
                },
                "parameters": [
                    {
                        "name": "__IMTCONN__",
                        "type": "account:apify2,apify",
                        "label": "Connection",
                        "required": true
                    }
                ],
                "expect": [
                    {
                        "name": "actor_search_type",
                        "type": "select",
                        "label": "Search Actors from",
                        "required": true,
                        "validate": {
                            "enum": [
                                "user",
                                "store"
                            ]
                        }
                    },
                    {
                        "name": "runSync",
                        "type": "boolean",
                        "label": "Run synchronously",
                        "required": true
                    },
                    {
                        "name": "build",
                        "type": "text",
                        "label": "Build"
                    },
                    {
                        "name": "timeout",
                        "type": "uinteger",
                        "label": "Timeout"
                    },
                    {
                        "name": "memory",
                        "type": "select",
                        "label": "Memory",
                        "validate": {
                            "enum": [
                                128,
                                256,
                                512,
                                1024,
                                2048,
                                4096,
                                8192,
                                16384,
                                32768
                            ]
                        }
                    },
                    {
                        "name": "actorId",
                        "type": "select",
                        "label": "Actor",
                        "required": true
                    },
                    {
                        "name": "inputBody9Sk4JJhEma9vBKqrg",
                        "type": "text",
                        "label": "Input JSON",
                        "required": true
                    },
                    {
                        "name": "maxTotalChargeUsd",
                        "type": "number",
                        "label": "Maximum cost per run"
                    },
                    {
                        "name": "maxItems",
                        "type": "hidden",
                        "label": "Maximum charged results"
                    }
                ]
            }
        },
        {
            "id": 6,
            "module": "apify:fetchDatasetItems",
            "version": 1,
            "parameters": {
                "__IMTCONN__": 4002834
            },
            "mapper": {
                "type": "clean",
                "limit": "100",
                "format": "json",
                "datasetId": "{{5.defaultDatasetId}}"
            },
            "metadata": {
                "designer": {
                    "x": 900,
                    "y": 0
                },
                "restore": {
                    "expect": {
                        "type": {
                            "mode": "chose",
                            "label": "Clean"
                        },
                        "format": {
                            "mode": "chose",
                            "label": "JSON"
                        }
                    },
                    "parameters": {
                        "__IMTCONN__": {
                            "data": {
                                "scoped": "true",
                                "connection": "apify"
                            },
                            "label": "My Apify API Token connection (borumohammed5@gmail.com)"
                        }
                    }
                },
                "parameters": [
                    {
                        "name": "__IMTCONN__",
                        "type": "account:apify2,apify",
                        "label": "Connection",
                        "required": true
                    }
                ],
                "expect": [
                    {
                        "name": "datasetId",
                        "type": "text",
                        "label": "Dataset ID",
                        "required": true
                    },
                    {
                        "name": "type",
                        "type": "select",
                        "label": "Data transformation",
                        "required": true,
                        "validate": {
                            "enum": [
                                "clean",
                                "simplified",
                                "none"
                            ]
                        }
                    },
                    {
                        "name": "format",
                        "type": "select",
                        "label": "Format",
                        "required": true,
                        "validate": {
                            "enum": [
                                "json",
                                "csv",
                                "html",
                                "xml",
                                "rss",
                                "xlsx"
                            ]
                        }
                    },
                    {
                        "name": "limit",
                        "type": "uinteger",
                        "label": "Limit",
                        "validate": {
                            "max": 100000,
                            "min": 1
                        }
                    },
                    {
                        "name": "offset",
                        "type": "uinteger",
                        "label": "Offset",
                        "validate": {
                            "min": 0
                        }
                    }
                ]
            }
        },
        {
            "id": 11,
            "module": "builtin:BasicAggregator",
            "version": 1,
            "parameters": {
                "feeder": 6
            },
            "mapper": {
                "domain": "{{6.domain}}",
                "emails": "{{6.emails}}",
                "phones": "{{6.phones}}",
                "threads": "{{6.threads}}",
                "tiktoks": "{{6.tiktoks}}",
                "twitters": "{{6.twitters}}",
                "youtubes": "{{6.youtubes}}",
                "facebooks": "{{6.facebooks}}",
                "linkedIns": "{{6.linkedIns}}",
                "whatsapps": "{{6.whatsapps}}",
                "instagrams": "{{6.instagrams}}",
                "city": "{{3.city}}",
                "title": "{{3.title}}",
                "street": "{{3.street}}",
                "address": "{{3.address}}"
            },
            "metadata": {
                "designer": {
                    "x": 1200,
                    "y": 0
                },
                "restore": {
                    "extra": {
                        "feeder": {
                            "label": "Apify - Get Dataset Items [6]"
                        },
                        "target": {
                            "label": "Custom"
                        }
                    }
                }
            }
        },
        {
            "id": 9,
            "module": "google-sheets:addRow",
            "version": 2,
            "parameters": {
                "__IMTCONN__": 3995470
            },
            "mapper": {
                "mode": "select",
                "insertUnformatted": false,
                "valueInputOption": "USER_ENTERED",
                "insertDataOption": "INSERT_ROWS",
                "from": "drive",
                "spreadsheetId": "/1OyK6daYcbTOTpdn0ej1DLD6waRCx7xTcO3EoVEADEJo",
                "sheetId": "Sheet1",
                "includesHeaders": true,
                "values": {
                    "0": "{{11.array[].title}}",
                    "1": "{{11.array[].phones}}",
                    "2": "{{11.array[].emails}}",
                    "3": "{{11.array[].linkedIns}}",
                    "4": "{{11.array[].facebooks}}",
                    "5": "{{11.array[].instagrams}}"
                }
            },
            "metadata": {
                "designer": {
                    "x": 1491,
                    "y": 3
                },
                "restore": {
                    "parameters": {
                        "__IMTCONN__": {
                            "label": "My Google connection (ratimboru@gmail.com)",
                            "data": {
                                "scoped": "true",
                                "connection": "google"
                            }
                        }
                    },
                    "expect": {
                        "mode": {
                            "label": "Search by path"
                        },
                        "insertUnformatted": {
                            "mode": "chose"
                        },
                        "valueInputOption": {
                            "mode": "chose",
                            "label": "User entered"
                        },
                        "insertDataOption": {
                            "mode": "chose",
                            "label": "Insert rows"
                        },
                        "from": {
                            "label": "My Drive"
                        },
                        "spreadsheetId": {
                            "path": [
                                "Apify"
                            ]
                        },
                        "sheetId": {
                            "label": "Sheet1"
                        },
                        "includesHeaders": {
                            "nested": [
                                {
                                    "name": "values",
                                    "spec": [
                                        {
                                            "name": "0",
                                            "type": "text",
                                            "label": "NAME (A)"
                                        },
                                        {
                                            "name": "1",
                                            "type": "text",
                                            "label": "PHONE (B)"
                                        },
                                        {
                                            "name": "2",
                                            "type": "text",
                                            "label": "EMAIL  (C)"
                                        },
                                        {
                                            "name": "3",
                                            "type": "text",
                                            "label": "LINKEDIN (D)"
                                        },
                                        {
                                            "name": "4",
                                            "type": "text",
                                            "label": "FACEBOOK  (E)"
                                        },
                                        {
                                            "name": "5",
                                            "type": "text",
                                            "label": "INSTAGRAM (F)"
                                        },
                                        {
                                            "name": "6",
                                            "type": "text",
                                            "label": "(G)"
                                        },
                                        {
                                            "name": "7",
                                            "type": "text",
                                            "label": "(H)"
                                        },
                                        {
                                            "name": "8",
                                            "type": "text",
                                            "label": "(I)"
                                        },
                                        {
                                            "name": "9",
                                            "type": "text",
                                            "label": "(J)"
                                        },
                                        {
                                            "name": "10",
                                            "type": "text",
                                            "label": "(K)"
                                        },
                                        {
                                            "name": "11",
                                            "type": "text",
                                            "label": "(L)"
                                        },
                                        {
                                            "name": "12",
                                            "type": "text",
                                            "label": "(M)"
                                        },
                                        {
                                            "name": "13",
                                            "type": "text",
                                            "label": "(N)"
                                        },
                                        {
                                            "name": "14",
                                            "type": "text",
                                            "label": "(O)"
                                        },
                                        {
                                            "name": "15",
                                            "type": "text",
                                            "label": "(P)"
                                        },
                                        {
                                            "name": "16",
                                            "type": "text",
                                            "label": "(Q)"
                                        },
                                        {
                                            "name": "17",
                                            "type": "text",
                                            "label": "(R)"
                                        },
                                        {
                                            "name": "18",
                                            "type": "text",
                                            "label": "(S)"
                                        },
                                        {
                                            "name": "19",
                                            "type": "text",
                                            "label": "(T)"
                                        },
                                        {
                                            "name": "20",
                                            "type": "text",
                                            "label": "(U)"
                                        },
                                        {
                                            "name": "21",
                                            "type": "text",
                                            "label": "(V)"
                                        },
                                        {
                                            "name": "22",
                                            "type": "text",
                                            "label": "(W)"
                                        },
                                        {
                                            "name": "23",
                                            "type": "text",
                                            "label": "(X)"
                                        },
                                        {
                                            "name": "24",
                                            "type": "text",
                                            "label": "(Y)"
                                        },
                                        {
                                            "name": "25",
                                            "type": "text",
                                            "label": "(Z)"
                                        }
                                    ],
                                    "type": "collection",
                                    "label": "Values"
                                }
                            ],
                            "label": "Yes"
                        }
                    }
                },
                "parameters": [
                    {
                        "name": "__IMTCONN__",
                        "type": "account:google",
                        "label": "Connection",
                        "required": true
                    }
                ],
                "expect": [
                    {
                        "name": "mode",
                        "type": "select",
                        "label": "Search Method",
                        "required": true,
                        "validate": {
                            "enum": [
                                "select",
                                "fromAll",
                                "map"
                            ]
                        }
                    },
                    {
                        "name": "insertUnformatted",
                        "type": "boolean",
                        "label": "Unformatted",
                        "required": true
                    },
                    {
                        "name": "valueInputOption",
                        "type": "select",
                        "label": "Value input option",
                        "validate": {
                            "enum": [
                                "USER_ENTERED",
                                "RAW"
                            ]
                        }
                    },
                    {
                        "name": "insertDataOption",
                        "type": "select",
                        "label": "Insert data option",
                        "validate": {
                            "enum": [
                                "INSERT_ROWS",
                                "OVERWRITE"
                            ]
                        }
                    },
                    {
                        "name": "from",
                        "type": "select",
                        "label": "Drive",
                        "required": true,
                        "validate": {
                            "enum": [
                                "drive",
                                "share",
                                "team"
                            ]
                        }
                    },
                    {
                        "name": "spreadsheetId",
                        "type": "file",
                        "label": "Spreadsheet ID",
                        "required": true
                    },
                    {
                        "name": "sheetId",
                        "type": "select",
                        "label": "Sheet Name",
                        "required": true
                    },
                    {
                        "name": "includesHeaders",
                        "type": "select",
                        "label": "Table contains headers",
                        "required": true,
                        "validate": {
                            "enum": [
                                true,
                                false
                            ]
                        }
                    },
                    {
                        "name": "values",
                        "type": "collection",
                        "label": "Values",
                        "spec": [
                            {
                                "name": "0",
                                "type": "text",
                                "label": "NAME (A)"
                            },
                            {
                                "name": "1",
                                "type": "text",
                                "label": "PHONE (B)"
                            },
                            {
                                "name": "2",
                                "type": "text",
                                "label": "EMAIL  (C)"
                            },
                            {
                                "name": "3",
                                "type": "text",
                                "label": "LINKEDIN (D)"
                            },
                            {
                                "name": "4",
                                "type": "text",
                                "label": "FACEBOOK  (E)"
                            },
                            {
                                "name": "5",
                                "type": "text",
                                "label": "INSTAGRAM (F)"
                            },
                            {
                                "name": "6",
                                "type": "text",
                                "label": "(G)"
                            },
                            {
                                "name": "7",
                                "type": "text",
                                "label": "(H)"
                            },
                            {
                                "name": "8",
                                "type": "text",
                                "label": "(I)"
                            },
                            {
                                "name": "9",
                                "type": "text",
                                "label": "(J)"
                            },
                            {
                                "name": "10",
                                "type": "text",
                                "label": "(K)"
                            },
                            {
                                "name": "11",
                                "type": "text",
                                "label": "(L)"
                            },
                            {
                                "name": "12",
                                "type": "text",
                                "label": "(M)"
                            },
                            {
                                "name": "13",
                                "type": "text",
                                "label": "(N)"
                            },
                            {
                                "name": "14",
                                "type": "text",
                                "label": "(O)"
                            },
                            {
                                "name": "15",
                                "type": "text",
                                "label": "(P)"
                            },
                            {
                                "name": "16",
                                "type": "text",
                                "label": "(Q)"
                            },
                            {
                                "name": "17",
                                "type": "text",
                                "label": "(R)"
                            },
                            {
                                "name": "18",
                                "type": "text",
                                "label": "(S)"
                            },
                            {
                                "name": "19",
                                "type": "text",
                                "label": "(T)"
                            },
                            {
                                "name": "20",
                                "type": "text",
                                "label": "(U)"
                            },
                            {
                                "name": "21",
                                "type": "text",
                                "label": "(V)"
                            },
                            {
                                "name": "22",
                                "type": "text",
                                "label": "(W)"
                            },
                            {
                                "name": "23",
                                "type": "text",
                                "label": "(X)"
                            },
                            {
                                "name": "24",
                                "type": "text",
                                "label": "(Y)"
                            },
                            {
                                "name": "25",
                                "type": "text",
                                "label": "(Z)"
                            }
                        ]
                    }
                ]
            }
        }
    ],
    "metadata": {
        "instant": false,
        "version": 1,
        "scenario": {
            "roundtrips": 1,
            "maxErrors": 3,
            "autoCommit": true,
            "autoCommitTriggerLast": true,
            "sequential": false,
            "slots": null,
            "confidential": false,
            "dataloss": false,
            "dlq": false,
            "freshVariables": false
        },
        "designer": {
            "orphans": []
        },
        "zone": "eu1.make.com",
        "notes": []
    }
}